pinguino/__init__.py
pinguino/dev.py
pinguino/pinguino.bat
pinguino/pinguino.py
pinguino/pinguino_cmd.py
pinguino/pinguino_reset.py
pinguino/regression.sh
pinguino/test.py
pinguino/version.py
pinguino/docs/ide/getting_around.html
pinguino/docs/ide/shortcuts_commands.html
pinguino/docs/index/graphical_environment.html
pinguino/docs/index/how_to.html
pinguino/docs/index/index.html
pinguino/docs/index/text_environment.html
pinguino/docs/index/tools.html
pinguino/docs/notyetready/notyetready.html
pinguino/docs/static/css/bootstrap.min.css
pinguino/docs/static/css/styles.css
pinguino/docs/static/images/frame.png
pinguino/docs/static/images/frame1.png
pinguino/docs/static/images/frame2.png
pinguino/docs/static/images/frame3.png
pinguino/docs/static/images/frame4.png
pinguino/docs/static/images/frame5.png
pinguino/docs/static/images/frame6.png
pinguino/docs/static/images/frame7.png
pinguino/multilanguage/pinguino_es.qm
pinguino/multilanguage/pinguino_fr.qm
pinguino/multilanguage/pinguino_ja.qm
pinguino/qtgui/__init__.py
pinguino/qtgui/config/pinguino.linux.conf
pinguino/qtgui/config/pinguino.macosx.conf
pinguino/qtgui/config/pinguino.windows.conf
pinguino/qtgui/frames/__init__.py
pinguino/qtgui/frames/about.py
pinguino/qtgui/frames/blocks_widget.py
pinguino/qtgui/frames/grafical_widget.py
pinguino/qtgui/frames/insert_block.py
pinguino/qtgui/frames/library_template.py
pinguino/qtgui/frames/main.py
pinguino/qtgui/frames/select_area.py
pinguino/qtgui/frames/submit_bug.py
pinguino/qtgui/gide/__init__.py
pinguino/qtgui/gide/app/__init__.py
pinguino/qtgui/gide/app/blocks.py
pinguino/qtgui/gide/app/code2blocks.py
pinguino/qtgui/gide/app/graphical.py
pinguino/qtgui/gide/app/tool_area.py
pinguino/qtgui/gide/app/work_area.py
pinguino/qtgui/gide/bloques/.config
pinguino/qtgui/gide/bloques/__init__.py
pinguino/qtgui/gide/bloques/blockConstructor.py
pinguino/qtgui/gide/bloques/constructor.py
pinguino-12.0.32.dist-info/DESCRIPTION.rst
pinguino-12.0.32.dist-info/METADATA
pinguino-12.0.32.dist-info/RECORD
pinguino-12.0.32.dist-info/WHEEL
pinguino-12.0.32.dist-info/metadata.json
pinguino-12.0.32.dist-info/top_level.txt
