Metadata-Version: 2.0
Name: pinguino
Version: 12.0.32
Summary: Open Hardware Electronics Prototyping Platform, Open Source Integrated Development Environment (IDE)
Home-page: http://www.pinguino.cc/
Author: Yeison Cardona
Author-email: yeisoneng@gmail.com
License: GPLv2
Keywords: microchip,electronic,prototyping,IDE
Platform: UNKNOWN
Classifier: Environment :: X11 Applications :: Qt
Classifier: Intended Audience :: Developers
Classifier: License :: OSI Approved :: GNU General Public License v2 (GPLv2)
Classifier: Operating System :: POSIX :: Linux
Classifier: Operating System :: Microsoft :: Windows
Classifier: Operating System :: MacOS
Classifier: Programming Language :: Python
Classifier: Topic :: Software Development
Classifier: Topic :: Software Development :: Code Generators
Classifier: Topic :: Software Development :: Compilers
Classifier: Topic :: Software Development :: Debuggers
Requires-Dist: pyusb (==1.0.0b2)
Provides-Extra: gui
Requires-Dist: pyside; extra == 'gui'
